[
  {
    "path": "/tabulation",
    "name": "Tabulation",
    "description": "Explore data tables with advanced features.",
    "component": "Tabulation"
  },
  {
    "path": "/drag-and-drop",
    "name": "Drag and Drop",
    "description": "Interact with items using drag-and-drop functionality.",
    "component": "DragAndDrop"
  },
  {
    "path": "/todo-list",
    "name": "Todo List",
    "description": "Manage tasks with advanced features and local storage.",
    "component": "TodoList"
  },
  {
    "path": "/markdown-editor",
    "name": "Markdown Editor",
    "description": "Write and preview Markdown with advanced features.",
    "component": "MarkdownEditor"
  },
  {
    "path": "/file-uploader",
    "name": "File Uploader",
    "description": "Upload and preview files with advanced drag-and-drop functionality.",
    "component": "FileUploader"
  },
  {
    "path": "/tic-tac-toe",
    "name": "Tic-Tac-Toe",
    "description": "Play Tic-Tac-Toe against a friend or AI.",
    "component": "TicTacToe"
  }
]
